django_tmdb/__init__.py
django_tmdb/admin.py
django_tmdb/apps.py
django_tmdb/models.py
django_tmdb/views.py
django_tmdb/migrations/0001_initial.py
django_tmdb/migrations/__init__.py
django_tmdb/templates/tmdb_tags/_recent_media.html
django_tmdb/templatetags/__init__.py
django_tmdb/templatetags/tmdb_tags.py
django_tmdb/tests/__init__.py
django_tmdb/tests/settings.py
django_tmdb/tests/test_api_connection.py
django_tmdb/tests/test_template_tag.py
django_tmdb/tests/test_app/__init__.py
django_tmdb/tests/test_app/models.py
django_tmdb/tests/test_app/templates/400.html
django_tmdb/tests/test_app/templates/500.html
django_tmdb3-0.1.0.dist-info/DESCRIPTION.rst
django_tmdb3-0.1.0.dist-info/METADATA
django_tmdb3-0.1.0.dist-info/RECORD
django_tmdb3-0.1.0.dist-info/WHEEL
django_tmdb3-0.1.0.dist-info/metadata.json
django_tmdb3-0.1.0.dist-info/top_level.txt
tmdb3/__init__.py
tmdb3/cache.py
tmdb3/cache_engine.py
tmdb3/cache_file.py
tmdb3/cache_null.py
tmdb3/locales.py
tmdb3/pager.py
tmdb3/request.py
tmdb3/tmdb_api.py
tmdb3/tmdb_auth.py
tmdb3/tmdb_exceptions.py
tmdb3/util.py
